sphericalrht/__init__.py
sphericalrht/py.typed
sphericalrht/spherical_rht.py
sphericalrht/utils.py
sphericalrht-2.0.1.dist-info/LICENSE
sphericalrht-2.0.1.dist-info/METADATA
sphericalrht-2.0.1.dist-info/WHEEL
sphericalrht-2.0.1.dist-info/top_level.txt
sphericalrht-2.0.1.dist-info/RECORD
